{
  "id": "easy-george-w-bush",
  "title": "George W Bush",
  "packId": "easy",
  "packTitle": "Easy",
  "theme": "Everyday Life & Personal Experience",
  "questionCount": 20,
  "questions": [
    "What do you think of George W Bush?",
    "What do you think the rest of the world thinks of him?",
    "What are George W Bush's strong points?",
    "What are his weak points?",
    "Do you think George W Bush is a good speaker?",
    "What do you think when you see him on TV?",
    "Do you think George W Bush has been good for the world?",
    "Some think George W Bush is a war criminal. What do you think?",
    "Do you think he was right to invade Afghanistan and Iraq?",
    "What image of George W Bush sticks in your mind most? Why?",
    "Is George W Bush a good US President?",
    "What adjectives would you use to describe George W Bush?",
    "What do you know about George W Bush's life before he became President?",
    "What mistakes do you think he has made?",
    "If he weren't President, what job would he be best suited to?",
    "Do you know what 'Bushisms' are and do you know any?",
    "Bush said: \"I know the human being and fish can coexist peacefully.\" What do you think he meant by this?",
    "What do you think George W Bush thinks of other world leaders?",
    "What are Bush's biggest successes?",
    "What questions would you like to ask George W Bush?"
  ],
  "sourceFile": "easy_familiar_concrete_personal.pdf"
}
